flask_ini.py
setup.py
Flask_ini.egg-info/PKG-INFO
Flask_ini.egg-info/SOURCES.txt
Flask_ini.egg-info/dependency_links.txt
Flask_ini.egg-info/not-zip-safe
Flask_ini.egg-info/requires.txt
Flask_ini.egg-info/top_level.txt