Metadata-Version: 1.1
Name: Flask-ini
Version: 0.1.0
Summary: Allow Flask to be configured with ConfigParser ini files
Home-page: https://github.com/trendmicro/flask-ini
Author: Rich Daley
Author-email: rich@richd.me
License: BSD
Platform: any
Classifier: Environment :: Web Environment
Classifier: Intended Audience :: Developers
Classifier: License :: OSI Approved :: BSD License
Classifier: Operating System :: OS Independent
Classifier: Programming Language :: Python
Classifier: Topic :: Internet :: WWW/HTTP :: Dynamic Content
Classifier: Topic :: Software Development :: Libraries :: Python Modules
